shun_notebook/__init__.py
shun_notebook/_nbdev.py
shun_notebook-0.2.55.dist-info/LICENSE.md
shun_notebook-0.2.55.dist-info/METADATA
shun_notebook-0.2.55.dist-info/WHEEL
shun_notebook-0.2.55.dist-info/entry_points.txt
shun_notebook-0.2.55.dist-info/top_level.txt
shun_notebook-0.2.55.dist-info/RECORD
