Metadata-Version: 2.1
Name: shun-notebook
Version: 0.2.55
Summary: My Study Notebook
Home-page: https://github.com/shunkakinoki/shun_notebook
Author: Shun Kakinoki
Author-email: shunkakinoki@gmail.com
License: Apache Software License 2.0
Keywords: Notebook
Platform: UNKNOWN
Classifier: Development Status :: 2 - Pre-Alpha
Classifier: Intended Audience :: Developers
Classifier: License :: OSI Approved :: Apache Software License
Classifier: Natural Language :: English
Classifier: Programming Language :: Python :: 3.7
Classifier: Programming Language :: Python :: 3.8
Requires-Python: >=3.7
